vtable/__init__.py
vtable/checkablecombo.py
vtable/colfilters.py
vtable/filteredtablemodel.py
vtable/loaders.py
vtable/main.py
vtable/newtable.py
vtable/selector.py
vtable/supertable.py
vtable-0.1.6.dist-info/entry_points.txt
vtable-0.1.6.dist-info/LICENSE
vtable-0.1.6.dist-info/WHEEL
vtable-0.1.6.dist-info/METADATA
vtable-0.1.6.dist-info/RECORD
